spin_templete/__init__.py
spin_templete/templete.py
spin_templete-0.1.2.dist-info/METADATA
spin_templete-0.1.2.dist-info/WHEEL
spin_templete-0.1.2.dist-info/top_level.txt
spin_templete-0.1.2.dist-info/RECORD
