Metadata-Version: 2.1
Name: spin-templete
Version: 0.1.2
Summary: spin templete is the layer of Spin-python-sdk for render html
Home-page: UNKNOWN
Author: mominiqbal1234
Author-email: <mominiqbal1214@gmail.com>
License: UNKNOWN
Keywords: spin-python-sdk,spinpython,python webassembly,webassembly,webassembly in python,webassembly api,build python webassembly api,python to webassembly
Platform: UNKNOWN
Classifier: Development Status :: 1 - Planning
Classifier: Intended Audience :: Developers
Classifier: Programming Language :: Python :: 3
Classifier: Operating System :: Unix
Classifier: Operating System :: MacOS :: MacOS X
Classifier: Operating System :: Microsoft :: Windows
Requires-Dist: Jinja2 (==3.1.3)
Requires-Dist: componentize-py (==0.13.2)
Requires-Dist: mypy (==1.8.0)
Requires-Dist: spin-sdk (==3.0.0)
